dapr/ext/grpc/__init__.py
dapr/ext/grpc/_health_servicer.py
dapr/ext/grpc/_servicer.py
dapr/ext/grpc/app.py
dapr/ext/grpc/py.typed
dapr/ext/grpc/version.py
dapr_ext_grpc_dev-1.16.0.dev60.dist-info/licenses/LICENSE
dapr_ext_grpc_dev-1.16.0.dev60.dist-info/METADATA
dapr_ext_grpc_dev-1.16.0.dev60.dist-info/WHEEL
dapr_ext_grpc_dev-1.16.0.dev60.dist-info/top_level.txt
dapr_ext_grpc_dev-1.16.0.dev60.dist-info/RECORD
